calchem/__init__.py
calchem/basic_calchem.py
calchem-0.0.2.dist-info/LICENSE
calchem-0.0.2.dist-info/METADATA
calchem-0.0.2.dist-info/WHEEL
calchem-0.0.2.dist-info/top_level.txt
calchem-0.0.2.dist-info/RECORD
