Metadata-Version: 2.1
Name: calchem
Version: 0.0.2
Summary: A Python module to calculate chemical formulas
Home-page: https://pypi.org/user/sepi3773/
Author: sepi3773
Author-email: author@example.com
License: UNKNOWN
Project-URL: Bug Tracker, https://pypi.org/user/sepi3773/
Platform: UNKNOWN
Classifier: Programming Language :: Python :: 3
Classifier: License :: OSI Approved :: MIT License
Classifier: Operating System :: OS Independent
Requires-Python: >=3.6
License-File: LICENSE
